omar6995_browserforge/__init__.py
omar6995_browserforge/bayesian_network.py
omar6995_browserforge/download.py
omar6995_browserforge/fingerprints/__init__.py
omar6995_browserforge/fingerprints/generator.py
omar6995_browserforge/headers/__init__.py
omar6995_browserforge/headers/generator.py
omar6995_browserforge/headers/utils.py
omar6995_browserforge/injectors/__init__.py
omar6995_browserforge/injectors/playwright/__init__.py
omar6995_browserforge/injectors/playwright/injector.py
omar6995_browserforge/injectors/pyppeteer/__init__.py
omar6995_browserforge/injectors/pyppeteer/injector.py
omar6995_browserforge/injectors/undetected_playwright/__init__.py
omar6995_browserforge/injectors/undetected_playwright/injector.py
omar6995_browserforge/injectors/utils.py
omar6995_browserforge/py.typed
omar6995_browserforge-1.2.10.dist-info/LICENSE
omar6995_browserforge-1.2.10.dist-info/METADATA
omar6995_browserforge-1.2.10.dist-info/WHEEL
omar6995_browserforge-1.2.10.dist-info/RECORD
